logqueue/__init__.py
logqueue-0.0.4.dist-info/METADATA
logqueue-0.0.4.dist-info/WHEEL
logqueue-0.0.4.dist-info/licenses/LICENSE
logqueue-0.0.4.dist-info/RECORD
