Metadata-Version: 2.1
Name: logqueue
Version: 0.0.4
Summary: Log Queue
Project-URL: Homepage, https://github.com/chorong8883/logqueue
Author-email: Chor <chorong8883@gmail.com>
License-File: LICENSE
Keywords: log,log q,log queue,logger,logger q,logger queue,logging,logging q,logging queue,logqueue,queue
Classifier: License :: OSI Approved :: MIT License
Classifier: Operating System :: MacOS
Classifier: Operating System :: POSIX :: Linux
Classifier: Programming Language :: Python :: 3.10
Requires-Python: >=3.10
